README.rst
setup.py
djehutylgtm/__init__.py
djehutylgtm/commands.py
djehutylgtm.egg-info/PKG-INFO
djehutylgtm.egg-info/SOURCES.txt
djehutylgtm.egg-info/dependency_links.txt
djehutylgtm.egg-info/entry_points.txt
djehutylgtm.egg-info/not-zip-safe
djehutylgtm.egg-info/requires.txt
djehutylgtm.egg-info/top_level.txt