Metadata-Version: 1.1
Name: djehutylgtm
Version: 0.0.1
Summary: djehutylgtm
Home-page: https://github.com/xica/djehutylgtm
Author: xica development team
Author-email: info@xica.net
License: MIT
Platform: UNKNOWN
Classifier: Development Status :: 3 - Alpha
Classifier: Environment :: Web Environment
Classifier: Framework :: Pyramid
Classifier: Intended Audience :: Developers
Classifier: License :: OSI Approved :: MIT License
Classifier: Operating System :: POSIX :: Linux
Classifier: Programming Language :: Python
Classifier: Topic :: Communications :: Chat
